aevmod.cpython-38-x86_64-linux-gnu.so
aevmod-1.1.0.dist-info/LICENSE
aevmod-1.1.0.dist-info/AUTHORS
aevmod-1.1.0.dist-info/RECORD
aevmod-1.1.0.dist-info/top_level.txt
aevmod-1.1.0.dist-info/METADATA
aevmod-1.1.0.dist-info/WHEEL
