Metadata-Version: 2.1
Name: aevmod
Version: 1.1.0
Summary: Compute atomic environment vector (AEV) and its derivatives
Author: Habib Najm
Author-email: Habib N Najm <hnnajm@sandia.gov>, Christian J Devereux <cjdever@sandia.gov>, Carles Martí <cmartia@sandia.gov>
Maintainer-email: Carles Martí <cmartia@sandia.gov>, Habib N Najm <hnnajm@sandia.gov>, Christian J Devereux <cjdever@sandia.gov>
License: BSD 2-Clause License
Project-URL: homepage, https://github.com/sandialabs/aevmod/
Project-URL: documentation, https://github.com/sandialabs/aevmod/?tab=readme-ov-file#aevmod-package
Requires-Python: >=3.8
License-File: LICENSE
License-File: AUTHORS
Requires-Dist: numpy >=1.17.0
